snowpark_connect_deps_2/__init__.py
snowpark_connect_deps_2/jars/antlr4-runtime-4.9.3.jar
snowpark_connect_deps_2/jars/commons-cli-1.5.0.jar
snowpark_connect_deps_2/jars/commons-codec-1.16.1.jar
snowpark_connect_deps_2/jars/commons-collections-3.2.2.jar
snowpark_connect_deps_2/jars/commons-collections4-4.4.jar
snowpark_connect_deps_2/jars/commons-compiler-3.1.9.jar
snowpark_connect_deps_2/jars/commons-compress-1.26.0.jar
snowpark_connect_deps_2/jars/commons-crypto-1.1.0.jar
snowpark_connect_deps_2/jars/commons-dbcp-1.4.jar
snowpark_connect_deps_2/jars/commons-io-2.16.1.jar
snowpark_connect_deps_2/jars/commons-lang-2.6.jar
snowpark_connect_deps_2/jars/commons-lang3-3.12.0.jar
snowpark_connect_deps_2/jars/commons-logging-1.1.3.jar
snowpark_connect_deps_2/jars/commons-math3-3.6.1.jar
snowpark_connect_deps_2/jars/commons-pool-1.5.4.jar
snowpark_connect_deps_2/jars/commons-text-1.10.0.jar
snowpark_connect_deps_2/jars/hadoop-client-api-3.3.4.jar
snowpark_connect_deps_2/jars/jackson-annotations-2.15.2.jar
snowpark_connect_deps_2/jars/jackson-core-2.15.2.jar
snowpark_connect_deps_2/jars/jackson-core-asl-1.9.13.jar
snowpark_connect_deps_2/jars/jackson-databind-2.15.2.jar
snowpark_connect_deps_2/jars/jackson-dataformat-yaml-2.15.2.jar
snowpark_connect_deps_2/jars/jackson-datatype-jsr310-2.15.2.jar
snowpark_connect_deps_2/jars/jackson-module-scala_2.12-2.15.2.jar
snowpark_connect_deps_2/jars/json4s-ast_2.12-3.7.0-M11.jar
snowpark_connect_deps_2/jars/json4s-core_2.12-3.7.0-M11.jar
snowpark_connect_deps_2/jars/json4s-jackson_2.12-3.7.0-M11.jar
snowpark_connect_deps_2/jars/json4s-native_2.12-3.7.0-M11.jar
snowpark_connect_deps_2/jars/json4s-scalap_2.12-3.7.0-M11.jar
snowpark_connect_deps_2/jars/kryo-shaded-4.0.2.jar
snowpark_connect_deps_2/jars/log4j-1.2-api-2.20.0.jar
snowpark_connect_deps_2/jars/log4j-api-2.20.0.jar
snowpark_connect_deps_2/jars/log4j-core-2.20.0.jar
snowpark_connect_deps_2/jars/log4j-slf4j2-impl-2.20.0.jar
snowpark_connect_deps_2/jars/paranamer-2.8.3.jar
snowpark_connect_deps_2-3.56.2.dist-info/licenses/LICENSE-binary
snowpark_connect_deps_2-3.56.2.dist-info/licenses/LICENSE.txt
snowpark_connect_deps_2-3.56.2.dist-info/licenses/NOTICE-binary
snowpark_connect_deps_2-3.56.2.dist-info/METADATA
snowpark_connect_deps_2-3.56.2.dist-info/WHEEL
snowpark_connect_deps_2-3.56.2.dist-info/top_level.txt
snowpark_connect_deps_2-3.56.2.dist-info/RECORD
